pyBunniApi/__init__.py
pyBunniApi/client.py
pyBunniApi/error.py
pyBunniApi/py.typed
pyBunniApi/objects/__init__.py
pyBunniApi/objects/bankaccount.py
pyBunniApi/objects/category.py
pyBunniApi/objects/contact.py
pyBunniApi/objects/invoice.py
pyBunniApi/objects/invoicedesign.py
pyBunniApi/objects/project.py
pyBunniApi/objects/row.py
pyBunniApi/objects/tax_rate.py
pyBunniApi/objects/time.py
pyBunniApi/resources/__init__.py
pyBunniApi/resources/bank_accounts.py
pyBunniApi/resources/categories.py
pyBunniApi/resources/contacts.py
pyBunniApi/resources/invoice_designs.py
pyBunniApi/resources/invoices.py
pyBunniApi/resources/projects.py
pyBunniApi/resources/tax_rates.py
pyBunniApi/resources/time.py
pyBunniApi/tools/__init__.py
pyBunniApi/tools/case_convert.py
tests/__init__.py
tests/conftest.py
tests/test_bank_account.py
tests/test_categories.py
tests/test_client.py
tests/test_contact.py
tests/test_initiate_models.py
tests/test_invoice.py
tests/test_invoice_design.py
tests/test_project.py
tests/test_tax_rate.py
tests/test_time.py
pyBunniApi-1.2.6.dist-info/METADATA
pyBunniApi-1.2.6.dist-info/WHEEL
pyBunniApi-1.2.6.dist-info/top_level.txt
pyBunniApi-1.2.6.dist-info/RECORD
