Metadata-Version: 2.2
Name: pyBunniApi
Version: 1.2.6
Summary: A API Client for communicating with the Bunni accounting software
Home-page: https://github.com/sme4gle/pyBunniApi
Author: Mickael van Schie
Author-email: mickael.v.s.19@hotmail.com
License: BSD 2-clause
Requires-Dist: requests>=2.25.1
Dynamic: author
Dynamic: author-email
Dynamic: description
Dynamic: description-content-type
Dynamic: home-page
Dynamic: license
Dynamic: requires-dist
Dynamic: summary
